interactions_lavalink/__init__.py
interactions_lavalink/events.py
interactions_lavalink/extension.py
interactions_lavalink/player.py
interactions_lavalink-3.0.0.dist-info/LICENSE
interactions_lavalink-3.0.0.dist-info/METADATA
interactions_lavalink-3.0.0.dist-info/WHEEL
interactions_lavalink-3.0.0.dist-info/top_level.txt
interactions_lavalink-3.0.0.dist-info/RECORD
