Metadata-Version: 2.1
Name: interactions-lavalink
Version: 3.0.0
Summary: Lavalink support for interactions.py
Home-page: https://github.com/interactions-py/lavalink
Author: Damego
Author-email: damego.dev@gmail.com
License: MIT
Classifier: Intended Audience :: Developers
Classifier: License :: OSI Approved :: MIT License
Classifier: Natural Language :: English
Classifier: Operating System :: OS Independent
Classifier: Programming Language :: Python :: 3
Classifier: Programming Language :: Python :: 3.10
Classifier: Programming Language :: Python :: 3.11
Classifier: Topic :: Internet
Classifier: Topic :: Software Development :: Libraries :: Python Modules
Classifier: Topic :: Software Development :: Libraries
Classifier: Topic :: Utilities
Requires-Python: >=3.10
License-File: LICENSE
Requires-Dist: interactions.py <6.0.0,>=5.0.0
Requires-Dist: lavalink <6.0.0,>=5.0.0
